[
	{
		"division": "HANDBAGS",
		"upc": "098689481753",
		"category": "CORE LEATHER",
		"retail": "160",
		"curr": "USD",
		"description": "HALF-CIRCLE BAG IN NATURAL LEATHER",
		"color": "125",
		"color_description": "NATURAL",
		"style": "4IRU0016",
		"size": "U",
		"tray": "1",
		"enabled": "TRUE",
		"soldout": "FALSE"
	},
	{
		"division": "APPAREL",
		"upc": "716453378787",
		"category": "DRESS",
		"retail": "150",
		"curr": "USD",
		"description": "PLEATED SCOOPBACK DRESS",
		"color": "001",
		"color_description": "BLACK",
		"style": "4CMU0174",
		"size": "XS",
		"tray": "",
		"enabled": "TRUE",
		"soldout": "FALSE"
	},
	{
		"division": "APPAREL",
		"upc": "716453378763",
		"category": "DRESS",
		"retail": "150",
		"curr": "USD",
		"description": "PLEATED SCOOPBACK DRESS",
		"color": "001",
		"color_description": "BLACK",
		"style": "4CMU0174",
		"size": "S",
		"tray": "",
		"enabled": "TRUE",
		"soldout": "FALSE"
	},
	{
		"division": "APPAREL",
		"upc": "716453378756",
		"category": "DRESS",
		"retail": "150",
		"curr": "USD",
		"description": "PLEATED SCOOPBACK DRESS",
		"color": "001",
		"color_description": "BLACK",
		"style": "4CMU0174",
		"size": "M",
		"tray": "",
		"enabled": "TRUE",
		"soldout": "FALSE"
	},
	{
		"division": "APPAREL",
		"upc": "716453378749",
		"category": "DRESS",
		"retail": "150",
		"curr": "USD",
		"description": "PLEATED SCOOPBACK DRESS",
		"color": "001",
		"color_description": "BLACK",
		"style": "4CMU0174",
		"size": "L",
		"tray": "",
		"enabled": "TRUE",
		"soldout": "FALSE"
	},
	{
		"division": "APPAREL",
		"upc": "716453378985",
		"category": "DRESS",
		"retail": "150",
		"curr": "USD",
		"description": "PLEATED SCOOPBACK DRESS",
		"color": "298",
		"color_description": "BRIGHT PEACH",
		"style": "4CMU0174",
		"size": "XS",
		"tray": "",
		"enabled": "TRUE",
		"soldout": "FALSE"
	},
	{
		"division": "APPAREL",
		"upc": "716453378886",
		"category": "DRESS",
		"retail": "150",
		"curr": "USD",
		"description": "PLEATED SCOOPBACK DRESS",
		"color": "298",
		"color_description": "BRIGHT PEACH",
		"style": "4CMU0174",
		"size": "S",
		"tray": "",
		"enabled": "TRUE",
		"soldout": "FALSE"
	},
	{
		"division": "APPAREL",
		"upc": "716453378879",
		"category": "DRESS",
		"retail": "150",
		"curr": "USD",
		"description": "PLEATED SCOOPBACK DRESS",
		"color": "298",
		"color_description": "BRIGHT PEACH",
		"style": "4CMU0174",
		"size": "M",
		"tray": "",
		"enabled": "TRUE",
		"soldout": "FALSE"
	},
	{
		"division": "APPAREL",
		"upc": "716453378794",
		"category": "DRESS",
		"retail": "150",
		"curr": "USD",
		"description": "PLEATED SCOOPBACK DRESS",
		"color": "298",
		"color_description": "BRIGHT PEACH",
		"style": "4CMU0174",
		"size": "L",
		"tray": "",
		"enabled": "TRUE",
		"soldout": "FALSE"
	},
	{
		"division": "APPAREL",
		"upc": "716453379081",
		"category": "DRESS",
		"retail": "150",
		"curr": "USD",
		"description": "PLEATED SCOOPBACK DRESS",
		"color": "489",
		"color_description": "LIGHT TEAL",
		"style": "4CMU0174",
		"size": "XS",
		"tray": "",
		"enabled": "TRUE",
		"soldout": "FALSE"
	},
	{
		"division": "APPAREL",
		"upc": "716453379067",
		"category": "DRESS",
		"retail": "150",
		"curr": "USD",
		"description": "PLEATED SCOOPBACK DRESS",
		"color": "489",
		"color_description": "LIGHT TEAL",
		"style": "4CMU0174",
		"size": "S",
		"tray": "",
		"enabled": "TRUE",
		"soldout": "FALSE"
	},
	{
		"division": "APPAREL",
		"upc": "716453379050",
		"category": "DRESS",
		"retail": "150",
		"curr": "USD",
		"description": "PLEATED SCOOPBACK DRESS",
		"color": "489",
		"color_description": "LIGHT TEAL",
		"style": "4CMU0174",
		"size": "M",
		"tray": "",
		"enabled": "TRUE",
		"soldout": "FALSE"
	},
	{
		"division": "APPAREL",
		"upc": "716453379043",
		"category": "DRESS",
		"retail": "150",
		"curr": "USD",
		"description": "PLEATED SCOOPBACK DRESS",
		"color": "489",
		"color_description": "LIGHT TEAL",
		"style": "4CMU0174",
		"size": "L",
		"tray": "",
		"enabled": "TRUE",
		"soldout": "FALSE"
	},
	{
		"division": "APPAREL",
		"upc": "716453379180",
		"category": "DRESS",
		"retail": "150",
		"curr": "USD",
		"description": "PLEATED SCOOPBACK DRESS",
		"color": "701",
		"color_description": "YELLOW",
		"style": "4CMU0174",
		"size": "XS",
		"tray": "1",
		"enabled": "TRUE",
		"soldout": "FALSE"
	},
	{
		"division": "APPAREL",
		"upc": "716453379166",
		"category": "DRESS",
		"retail": "150",
		"curr": "USD",
		"description": "PLEATED SCOOPBACK DRESS",
		"color": "701",
		"color_description": "YELLOW",
		"style": "4CMU0174",
		"size": "S",
		"tray": "",
		"enabled": "TRUE",
		"soldout": "FALSE"
	},
	{
		"division": "APPAREL",
		"upc": "716453379159",
		"category": "DRESS",
		"retail": "150",
		"curr": "USD",
		"description": "PLEATED SCOOPBACK DRESS",
		"color": "701",
		"color_description": "YELLOW",
		"style": "4CMU0174",
		"size": "M",
		"tray": "",
		"enabled": "TRUE",
		"soldout": "FALSE"
	},
	{
		"division": "APPAREL",
		"upc": "716453379142",
		"category": "DRESS",
		"retail": "150",
		"curr": "USD",
		"description": "PLEATED SCOOPBACK DRESS",
		"color": "701",
		"color_description": "YELLOW",
		"style": "4CMU0174",
		"size": "L",
		"tray": "",
		"enabled": "TRUE",
		"soldout": "FALSE"
	},
	{
		"division": "TECH",
		"upc": "098689483788",
		"category": "IPHONE",
		"retail": "25",
		"curr": "USD",
		"description": "IPHONE 5 CASE",
		"color": "718",
		"color_description": "DRESSED IN YELLOW",
		"style": "4LRU0004",
		"size": "U",
		"tray": "1",
		"enabled": "TRUE",
		"soldout": "FALSE"
	},
	{
		"division": "TECH",
		"upc": "098689483603",
		"category": "IPHONE",
		"retail": "25",
		"curr": "USD",
		"description": "IPHONE 4 CASE",
		"color": "718",
		"color_description": "DRESSED IN YELLOW",
		"style": "4LRU0003",
		"size": "U",
		"tray": "",
		"enabled": "TRUE",
		"soldout": "FALSE"
	},
	{
		"division": "WATCHES",
		"upc": "098686427693",
		"category": "FASHION",
		"retail": "50",
		"curr": "USD",
		"description": "MAY28TH & KATE SPADE SATURDAY WATCH",
		"color": "701",
		"color_description": "YELLOW",
		"style": "4URU0001",
		"size": "U",
		"tray": "1",
		"enabled": "TRUE",
		"soldout": "FALSE"
	},
	{
		"division": "JEWELRY",
		"upc": "098686426214",
		"category": "FASHION",
		"retail": "50",
		"curr": "USD",
		"description": "CORDED KNOT NECKLACE",
		"color": "701",
		"color_description": "YELLOW",
		"style": "4VRU0028",
		"size": "U",
		"tray": "1",
		"enabled": "TRUE",
		"soldout": "FALSE"
	},
	{
		"division": "HANDBAGS",
		"upc": "098689516271",
		"category": "BEACH BAGS",
		"retail": "85",
		"curr": "USD",
		"description": "CIRCLE-BOTTOM BEACH TOTE",
		"color": "701",
		"color_description": "YELLOW",
		"style": "4IRU0031",
		"size": "U",
		"tray": "1",
		"enabled": "TRUE",
		"soldout": "FALSE"
	},
	{
		"division": "SLGS",
		"upc": "098689517513",
		"category": "CORE FABRIC",
		"retail": "25",
		"curr": "USD",
		"description": "ZIPPERED POUCH",
		"color": "701",
		"color_description": "YELLOW",
		"style": "4JRU0087",
		"size": "U",
		"tray": "1",
		"enabled": "TRUE",
		"soldout": "FALSE"
	},
	{
		"division": "HOME",
		"upc": "098689521978",
		"category": "TABLETOP",
		"retail": "60",
		"curr": "USD",
		"description": "CORD HANDLE BUCKET",
		"color": "922",
		"color_description": "CLEAR",
		"style": "4WRU0060",
		"size": "U",
		"tray": "1",
		"enabled": "TRUE",
		"soldout": "FALSE"
	},
	{
		"division": "HOME",
		"upc": "098689522029",
		"category": "EXTRAS",
		"retail": "90",
		"curr": "USD",
		"description": "OVERSIZE PICNIC BLANKET IN PAINTED PLAID",
		"color": "470",
		"color_description": "PAINTED PLAID",
		"style": "4WRU0073",
		"size": "U",
		"tray": "1",
		"enabled": "TRUE",
		"soldout": "FALSE"
	},
	{
		"division": "HANDBAGS",
		"upc": "098689519524",
		"category": "CORE FABRIC",
		"retail": "170",
		"curr": "USD",
		"description": "THE WEEKENDER BAG",
		"color": "621",
		"color_description": "TRUE RED",
		"style": "4IRU0008",
		"size": "U",
		"tray": "1",
		"enabled": "TRUE",
		"soldout": "FALSE"
	},
	{
		"division": "HANDBAGS",
		"upc": "098689519890",
		"category": "FASHION FABRIC",
		"retail": "120",
		"curr": "USD",
		"description": "PICNIC TOTE",
		"color": "621",
		"color_description": "TRUE RED",
		"style": "4IRU0058",
		"size": "U",
		"tray": "1",
		"enabled": "TRUE",
		"soldout": "FALSE"
	},
	{
		"division": "APPAREL",
		"upc": "716453399812",
		"category": "OUTERWEAR",
		"retail": "80",
		"curr": "USD",
		"description": "RAIN PONCHO IN BUSY FLORAL",
		"color": "924",
		"color_description": "BUSY FLORAL",
		"style": "4CMU0192",
		"size": "U",
		"tray": "1",
		"enabled": "TRUE",
		"soldout": "FALSE"
	},
	{
		"division": "FASHION ACCESSORIES",
		"upc": "098689517698",
		"category": "HATS",
		"retail": "35",
		"curr": "USD",
		"description": "BASEBALL CAP IN BUSY FLORAL",
		"color": "924",
		"color_description": "BUSY FLORAL",
		"style": "4KRU0021",
		"size": "U",
		"tray": "1",
		"enabled": "TRUE",
		"soldout": "FALSE"
	},
	{
		"division": "TECH",
		"upc": "098689520407",
		"category": "IPHONE",
		"retail": "25",
		"curr": "USD",
		"description": "IPHONE 5 CASE",
		"color": "924",
		"color_description": "BUSY FLORAL",
		"style": "4LRU0004",
		"size": "U",
		"tray": "1",
		"enabled": "TRUE",
		"soldout": "FALSE"
	},
	{
		"division": "TECH",
		"upc": "098689567778",
		"category": "IPHONE",
		"retail": "25",
		"curr": "USD",
		"description": "IPHONE 4 CASE",
		"color": "924",
		"color_description": "BUSY FLORAL",
		"style": "4LRU0003",
		"size": "U",
		"tray": "",
		"enabled": "TRUE",
		"soldout": "FALSE"
	},
	{
		"division": "HANDBAGS",
		"upc": "098689519579",
		"category": "CORE FABRIC",
		"retail": "40",
		"curr": "USD",
		"description": "THREE-WAY TOTE IN BUSY FLORAL",
		"color": "924",
		"color_description": "BUSY FLORAL",
		"style": "4IRU0009",
		"size": "U",
		"tray": "1",
		"enabled": "TRUE",
		"soldout": "FALSE"
	},
	{
		"division": "WATCHES",
		"upc": "098686427716",
		"category": "FASHION",
		"retail": "50",
		"curr": "USD",
		"description": "MAY28TH & KATE SPADE SATURDAY WATCH",
		"color": "924",
		"color_description": "BUSY FLORAL",
		"style": "4URU0001",
		"size": "U",
		"tray": "1",
		"enabled": "TRUE",
		"soldout": "FALSE"
	},
	{
		"division": "APPAREL",
		"upc": "098689521015",
		"category": "CORE",
		"retail": "65",
		"curr": "USD",
		"description": "KATE SPADE SATURDAY SNEAKS BY PF FLYERS",
		"color": "404",
		"color_description": "INDIGO FLORAL",
		"style": "4RRU0006",
		"size": "5",
		"tray": "1",
		"enabled": "TRUE",
		"soldout": "TRUE"
	},
	{
		"division": "APPAREL",
		"upc": "098689521022",
		"category": "CORE",
		"retail": "65",
		"curr": "USD",
		"description": "KATE SPADE SATURDAY SNEAKS BY PF FLYERS",
		"color": "404",
		"color_description": "INDIGO FLORAL",
		"style": "4RRU0006",
		"size": "6",
		"tray": "",
		"enabled": "TRUE",
		"soldout": "TRUE"
	},
	{
		"division": "APPAREL",
		"upc": "098689521039",
		"category": "CORE",
		"retail": "65",
		"curr": "USD",
		"description": "KATE SPADE SATURDAY SNEAKS BY PF FLYERS",
		"color": "404",
		"color_description": "INDIGO FLORAL",
		"style": "4RRU0006",
		"size": "7",
		"tray": "",
		"enabled": "TRUE",
		"soldout": "TRUE"
	},
	{
		"division": "APPAREL",
		"upc": "098689521046",
		"category": "CORE",
		"retail": "65",
		"curr": "USD",
		"description": "KATE SPADE SATURDAY SNEAKS BY PF FLYERS",
		"color": "404",
		"color_description": "INDIGO FLORAL",
		"style": "4RRU0006",
		"size": "8",
		"tray": "",
		"enabled": "TRUE",
		"soldout": "FALSE"
	},
	{
		"division": "APPAREL",
		"upc": "098689521053",
		"category": "CORE",
		"retail": "65",
		"curr": "USD",
		"description": "KATE SPADE SATURDAY SNEAKS BY PF FLYERS",
		"color": "404",
		"color_description": "INDIGO FLORAL",
		"style": "4RRU0006",
		"size": "9",
		"tray": "",
		"enabled": "TRUE",
		"soldout": "FALSE"
	},
	{
		"division": "APPAREL",
		"upc": "098689520995",
		"category": "CORE",
		"retail": "65",
		"curr": "USD",
		"description": "KATE SPADE SATURDAY SNEAKS BY PF FLYERS",
		"color": "404",
		"color_description": "INDIGO FLORAL",
		"style": "4RRU0006",
		"size": "10",
		"tray": "",
		"enabled": "TRUE",
		"soldout": "FALSE"
	},
	{
		"division": "APPAREL",
		"upc": "716453372068",
		"category": "SKIRT",
		"retail": "95",
		"curr": "USD",
		"description": "GATHER-ROUND MINI SKIRT IN BUSY FLORAL",
		"color": "924",
		"color_description": "BUSY FLORAL",
		"style": "4CMU0143",
		"size": "XS",
		"tray": "1",
		"enabled": "FALSE",
		"soldout": "FALSE"
	},
	{
		"division": "HANDBAGS",
		"upc": "098689516264",
		"category": "BEACH BAGS",
		"retail": "85",
		"curr": "USD",
		"description": "CIRCLE-BOTTOM BEACH TOTE",
		"color": "672",
		"color_description": "MAGENTA",
		"style": "4IRU0031",
		"size": "U",
		"tray": "",
		"enabled": "TRUE",
		"soldout": "FALSE"
	},
	{
		"division": "APPAREL",
		"upc": "716453368924",
		"category": "WOVEN TOP",
		"retail": "65",
		"curr": "USD",
		"description": "CROP-TIE TOP IN PAINTED CHECK",
		"color": "628",
		"color_description": "PAINTED CHECK",
		"style": "4CMU0124",
		"size": "XS",
		"tray": "1",
		"enabled": "FALSE",
		"soldout": "FALSE"
	},
	{
		"division": "APPAREL",
		"upc": "716453368900",
		"category": "WOVEN TOP",
		"retail": "65",
		"curr": "USD",
		"description": "CROP-TIE TOP IN PAINTED CHECK",
		"color": "628",
		"color_description": "PAINTED CHECK",
		"style": "4CMU0124",
		"size": "S",
		"tray": "",
		"enabled": "FALSE",
		"soldout": "FALSE"
	},
	{
		"division": "APPAREL",
		"upc": "716453368894",
		"category": "WOVEN TOP",
		"retail": "65",
		"curr": "USD",
		"description": "CROP-TIE TOP IN PAINTED CHECK",
		"color": "628",
		"color_description": "PAINTED CHECK",
		"style": "4CMU0124",
		"size": "M",
		"tray": "",
		"enabled": "FALSE",
		"soldout": "FALSE"
	},
	{
		"division": "APPAREL",
		"upc": "716453368887",
		"category": "WOVEN TOP",
		"retail": "65",
		"curr": "USD",
		"description": "CROP-TIE TOP IN PAINTED CHECK",
		"color": "628",
		"color_description": "PAINTED CHECK",
		"style": "4CMU0124",
		"size": "L",
		"tray": "",
		"enabled": "FALSE",
		"soldout": "FALSE"
	},
	{
		"division": "APPAREL",
		"upc": "098689521015",
		"category": "CORE",
		"retail": "65",
		"curr": "USD",
		"description": "KATE SPADE SATURDAY SNEAKS BY PF FLYERS",
		"color": "404",
		"color_description": "INDIGO FLORAL",
		"style": "4RRU0006",
		"size": "5",
		"tray": "2",
		"enabled": "TRUE",
		"soldout": "FALSE"
	},
	{
		"division": "APPAREL",
		"upc": "098689521022",
		"category": "CORE",
		"retail": "65",
		"curr": "USD",
		"description": "KATE SPADE SATURDAY SNEAKS BY PF FLYERS",
		"color": "404",
		"color_description": "INDIGO FLORAL",
		"style": "4RRU0006",
		"size": "6",
		"tray": "",
		"enabled": "TRUE",
		"soldout": "FALSE"
	},
	{
		"division": "APPAREL",
		"upc": "098689521039",
		"category": "CORE",
		"retail": "65",
		"curr": "USD",
		"description": "KATE SPADE SATURDAY SNEAKS BY PF FLYERS",
		"color": "404",
		"color_description": "INDIGO FLORAL",
		"style": "4RRU0006",
		"size": "7",
		"tray": "",
		"enabled": "TRUE",
		"soldout": "FALSE"
	},
	{
		"division": "APPAREL",
		"upc": "098689521046",
		"category": "CORE",
		"retail": "65",
		"curr": "USD",
		"description": "KATE SPADE SATURDAY SNEAKS BY PF FLYERS",
		"color": "404",
		"color_description": "INDIGO FLORAL",
		"style": "4RRU0006",
		"size": "8",
		"tray": "",
		"enabled": "TRUE",
		"soldout": "FALSE"
	},
	{
		"division": "APPAREL",
		"upc": "098689521053",
		"category": "CORE",
		"retail": "65",
		"curr": "USD",
		"description": "KATE SPADE SATURDAY SNEAKS BY PF FLYERS",
		"color": "404",
		"color_description": "INDIGO FLORAL",
		"style": "4RRU0006",
		"size": "9",
		"tray": "",
		"enabled": "TRUE",
		"soldout": "FALSE"
	},
	{
		"division": "APPAREL",
		"upc": "098689520995",
		"category": "CORE",
		"retail": "65",
		"curr": "USD",
		"description": "KATE SPADE SATURDAY SNEAKS BY PF FLYERS",
		"color": "404",
		"color_description": "INDIGO FLORAL",
		"style": "4RRU0006",
		"size": "10",
		"tray": "",
		"enabled": "TRUE",
		"soldout": "FALSE"
	},
	{
		"division": "APPAREL",
		"upc": "716453372068",
		"category": "SKIRT",
		"retail": "95",
		"curr": "USD",
		"description": "GATHER-ROUND MINI SKIRT IN BUSY FLORAL",
		"color": "924",
		"color_description": "BUSY FLORAL",
		"style": "4CMU0143",
		"size": "XS",
		"tray": "2",
		"enabled": "FALSE",
		"soldout": "FALSE"
	},
	{
		"division": "APPAREL",
		"upc": "716453368924",
		"category": "WOVEN TOP",
		"retail": "65",
		"curr": "USD",
		"description": "CROP-TIE TOP IN PAINTED CHECK",
		"color": "628",
		"color_description": "PAINTED CHECK",
		"style": "4CMU0124",
		"size": "XS",
		"tray": "2",
		"enabled": "FALSE",
		"soldout": "FALSE"
	},
	{
		"division": "APPAREL",
		"upc": "716453368900",
		"category": "WOVEN TOP",
		"retail": "65",
		"curr": "USD",
		"description": "CROP-TIE TOP IN PAINTED CHECK",
		"color": "628",
		"color_description": "PAINTED CHECK",
		"style": "4CMU0124",
		"size": "S",
		"tray": "",
		"enabled": "FALSE",
		"soldout": "FALSE"
	},
	{
		"division": "APPAREL",
		"upc": "716453368894",
		"category": "WOVEN TOP",
		"retail": "65",
		"curr": "USD",
		"description": "CROP-TIE TOP IN PAINTED CHECK",
		"color": "628",
		"color_description": "PAINTED CHECK",
		"style": "4CMU0124",
		"size": "M",
		"tray": "",
		"enabled": "FALSE",
		"soldout": "FALSE"
	},
	{
		"division": "APPAREL",
		"upc": "716453368887",
		"category": "WOVEN TOP",
		"retail": "65",
		"curr": "USD",
		"description": "CROP-TIE TOP IN PAINTED CHECK",
		"color": "628",
		"color_description": "PAINTED CHECK",
		"style": "4CMU0124",
		"size": "L",
		"tray": "",
		"enabled": "FALSE",
		"soldout": "FALSE"
	},
	{
		"division": "APPAREL",
		"upc": "716453366807",
		"category": "DRESS",
		"retail": "110",
		"curr": "USD",
		"description": "CALL ME DRESS",
		"color": "001",
		"color_description": "BLACK",
		"style": "4CMU0115",
		"size": "XS",
		"tray": "",
		"enabled": "TRUE",
		"soldout": "FALSE"
	},
	{
		"division": "APPAREL",
		"upc": "716453366784",
		"category": "DRESS",
		"retail": "110",
		"curr": "USD",
		"description": "CALL ME DRESS",
		"color": "001",
		"color_description": "BLACK",
		"style": "4CMU0115",
		"size": "S",
		"tray": "",
		"enabled": "TRUE",
		"soldout": "FALSE"
	},
	{
		"division": "APPAREL",
		"upc": "716453366777",
		"category": "DRESS",
		"retail": "110",
		"curr": "USD",
		"description": "CALL ME DRESS",
		"color": "001",
		"color_description": "BLACK",
		"style": "4CMU0115",
		"size": "M",
		"tray": "",
		"enabled": "TRUE",
		"soldout": "FALSE"
	},
	{
		"division": "APPAREL",
		"upc": "716453366760",
		"category": "DRESS",
		"retail": "110",
		"curr": "USD",
		"description": "CALL ME DRESS",
		"color": "001",
		"color_description": "BLACK",
		"style": "4CMU0115",
		"size": "L",
		"tray": "",
		"enabled": "TRUE",
		"soldout": "FALSE"
	},
	{
		"division": "APPAREL",
		"upc": "716453366906",
		"category": "DRESS",
		"retail": "110",
		"curr": "USD",
		"description": "CALL ME DRESS",
		"color": "046",
		"color_description": "HEATHER GREY",
		"style": "4CMU0115",
		"size": "XS",
		"tray": "2",
		"enabled": "TRUE",
		"soldout": "FALSE"
	},
	{
		"division": "APPAREL",
		"upc": "716453366883",
		"category": "DRESS",
		"retail": "110",
		"curr": "USD",
		"description": "CALL ME DRESS",
		"color": "046",
		"color_description": "HEATHER GREY",
		"style": "4CMU0115",
		"size": "S",
		"tray": "",
		"enabled": "TRUE",
		"soldout": "FALSE"
	},
	{
		"division": "APPAREL",
		"upc": "716453366876",
		"category": "DRESS",
		"retail": "110",
		"curr": "USD",
		"description": "CALL ME DRESS",
		"color": "046",
		"color_description": "HEATHER GREY",
		"style": "4CMU0115",
		"size": "M",
		"tray": "",
		"enabled": "TRUE",
		"soldout": "FALSE"
	},
	{
		"division": "APPAREL",
		"upc": "716453366869",
		"category": "DRESS",
		"retail": "110",
		"curr": "USD",
		"description": "CALL ME DRESS",
		"color": "046",
		"color_description": "HEATHER GREY",
		"style": "4CMU0115",
		"size": "L",
		"tray": "",
		"enabled": "TRUE",
		"soldout": "FALSE"
	},
	{
		"division": "APPAREL",
		"upc": "716453366951",
		"category": "DRESS",
		"retail": "110",
		"curr": "USD",
		"description": "CALL ME DRESS",
		"color": "088",
		"color_description": "MUSHROOM",
		"style": "4CMU0115",
		"size": "XS",
		"tray": "",
		"enabled": "TRUE",
		"soldout": "FALSE"
	},
	{
		"division": "APPAREL",
		"upc": "716453366937",
		"category": "DRESS",
		"retail": "110",
		"curr": "USD",
		"description": "CALL ME DRESS",
		"color": "088",
		"color_description": "MUSHROOM",
		"style": "4CMU0115",
		"size": "S",
		"tray": "",
		"enabled": "TRUE",
		"soldout": "FALSE"
	},
	{
		"division": "APPAREL",
		"upc": "716453366920",
		"category": "DRESS",
		"retail": "110",
		"curr": "USD",
		"description": "CALL ME DRESS",
		"color": "088",
		"color_description": "MUSHROOM",
		"style": "4CMU0115",
		"size": "M",
		"tray": "",
		"enabled": "TRUE",
		"soldout": "FALSE"
	},
	{
		"division": "APPAREL",
		"upc": "716453366913",
		"category": "DRESS",
		"retail": "110",
		"curr": "USD",
		"description": "CALL ME DRESS",
		"color": "088",
		"color_description": "MUSHROOM",
		"style": "4CMU0115",
		"size": "L",
		"tray": "",
		"enabled": "TRUE",
		"soldout": "FALSE"
	},
	{
		"division": "WATCHES",
		"upc": "716453367002",
		"category": "DRESS",
		"retail": "110",
		"curr": "USD",
		"description": "CALL ME DRESS",
		"color": "298",
		"color_description": "BRIGHT PEACH",
		"style": "4CMU0115",
		"size": "XS",
		"tray": "",
		"enabled": "TRUE",
		"soldout": "FALSE"
	},
	{
		"division": "home",
		"upc": "716453366982",
		"category": "DRESS",
		"retail": "110",
		"curr": "USD",
		"description": "CALL ME DRESS",
		"color": "298",
		"color_description": "BRIGHT PEACH",
		"style": "4CMU0115",
		"size": "S",
		"tray": "",
		"enabled": "TRUE",
		"soldout": "FALSE"
	},
	{
		"division": "SHOES",
		"upc": "716453366975",
		"category": "DRESS",
		"retail": "110",
		"curr": "USD",
		"description": "CALL ME DRESS",
		"color": "298",
		"color_description": "BRIGHT PEACH",
		"style": "4CMU0115",
		"size": "M",
		"tray": "",
		"enabled": "TRUE",
		"soldout": "FALSE"
	},
	{
		"division": "SHOES",
		"upc": "716453366968",
		"category": "DRESS",
		"retail": "110",
		"curr": "USD",
		"description": "CALL ME DRESS",
		"color": "298",
		"color_description": "BRIGHT PEACH",
		"style": "4CMU0115",
		"size": "L",
		"tray": "",
		"enabled": "TRUE",
		"soldout": "FALSE"
	},
	{
		"division": "SHOES",
		"upc": "098686407022",
		"category": "FASHION",
		"retail": "50",
		"curr": "USD",
		"description": "MAY28TH & KATE SPADE SATURDAY WATCH",
		"color": "103",
		"color_description": "WINDOWPANE",
		"style": "4URU0001",
		"size": "U",
		"tray": "2",
		"enabled": "TRUE",
		"soldout": "FALSE"
	},
	{
		"division": "SHOES",
		"upc": "098689486550",
		"category": "TABLETOP",
		"retail": "30",
		"curr": "USD",
		"description": "TALL GLASSES",
		"color": "103",
		"color_description": "WINDOWPANE",
		"style": "4WRU0030",
		"size": "U",
		"tray": "2",
		"enabled": "TRUE",
		"soldout": "FALSE"
	},
	{
		"division": "SHOES",
		"upc": "098689518237",
		"category": "CORE",
		"retail": "95",
		"curr": "USD",
		"description": "MULTI-STRAP SANDALS IN WHITE",
		"color": "100",
		"color_description": "WHITE",
		"style": "4RRU0012",
		"size": "5",
		"tray": "2",
		"enabled": "TRUE",
		"soldout": "TRUE"
	},
	{
		"division": "SHOES",
		"upc": "098689518244",
		"category": "CORE",
		"retail": "95",
		"curr": "USD",
		"description": "MULTI-STRAP SANDALS IN WHITE",
		"color": "100",
		"color_description": "WHITE",
		"style": "4RRU0012",
		"size": "6",
		"tray": "",
		"enabled": "TRUE",
		"soldout": "TRUE"
	},
	{
		"division": "JEWELRY",
		"upc": "098689518251",
		"category": "CORE",
		"retail": "95",
		"curr": "USD",
		"description": "MULTI-STRAP SANDALS IN WHITE",
		"color": "100",
		"color_description": "WHITE",
		"style": "4RRU0012",
		"size": "7",
		"tray": "",
		"enabled": "TRUE",
		"soldout": "FALSE"
	},
	{
		"division": "APPAREL",
		"upc": "098689518268",
		"category": "CORE",
		"retail": "95",
		"curr": "USD",
		"description": "MULTI-STRAP SANDALS IN WHITE",
		"color": "100",
		"color_description": "WHITE",
		"style": "4RRU0012",
		"size": "8",
		"tray": "",
		"enabled": "TRUE",
		"soldout": "FALSE"
	},
	{
		"division": "APPAREL",
		"upc": "098689518275",
		"category": "CORE",
		"retail": "95",
		"curr": "USD",
		"description": "MULTI-STRAP SANDALS IN WHITE",
		"color": "100",
		"color_description": "WHITE",
		"style": "4RRU0012",
		"size": "9",
		"tray": "",
		"enabled": "TRUE",
		"soldout": "FALSE"
	},
	{
		"division": "APPAREL",
		"upc": "098689518213",
		"category": "CORE",
		"retail": "95",
		"curr": "USD",
		"description": "MULTI-STRAP SANDALS IN WHITE",
		"color": "100",
		"color_description": "WHITE",
		"style": "4RRU0012",
		"size": "10",
		"tray": "",
		"enabled": "TRUE",
		"soldout": "TRUE"
	},
	{
		"division": "APPAREL",
		"upc": "098686426184",
		"category": "FASHION",
		"retail": "50",
		"curr": "USD",
		"description": "CORDED KNOT NECKLACE",
		"color": "001",
		"color_description": "BLACK",
		"style": "4VRU0028",
		"size": "U",
		"tray": "2",
		"enabled": "TRUE",
		"soldout": "FALSE"
	},
	{
		"division": "HANDBAGS",
		"upc": "716453314846",
		"category": "KNIT TOP",
		"retail": "30",
		"curr": "USD",
		"description": "SLIP NECK TEE IN STRIPE",
		"color": "007",
		"color_description": "BLACK & WHITE STRIPE",
		"style": "4CMU0008",
		"size": "XS",
		"tray": "2",
		"enabled": "TRUE",
		"soldout": "FALSE"
	},
	{
		"division": "apparel",
		"upc": "716453314822",
		"category": "KNIT TOP",
		"retail": "30",
		"curr": "USD",
		"description": "SLIP NECK TEE IN STRIPE",
		"color": "007",
		"color_description": "BLACK & WHITE STRIPE",
		"style": "4CMU0008",
		"size": "S",
		"tray": "",
		"enabled": "TRUE",
		"soldout": "FALSE"
	},
	{
		"division": "apparel",
		"upc": "716453314815",
		"category": "KNIT TOP",
		"retail": "30",
		"curr": "USD",
		"description": "SLIP NECK TEE IN STRIPE",
		"color": "007",
		"color_description": "BLACK & WHITE STRIPE",
		"style": "4CMU0008",
		"size": "M",
		"tray": "",
		"enabled": "TRUE",
		"soldout": "FALSE"
	},
	{
		"division": "apparel",
		"upc": "716453314808",
		"category": "KNIT TOP",
		"retail": "30",
		"curr": "USD",
		"description": "SLIP NECK TEE IN STRIPE",
		"color": "007",
		"color_description": "BLACK & WHITE STRIPE",
		"style": "4CMU0008",
		"size": "L",
		"tray": "",
		"enabled": "TRUE",
		"soldout": "FALSE"
	},
	{
		"division": "apparel",
		"upc": "098689481432",
		"category": "CORE FABRIC",
		"retail": "160",
		"curr": "USD",
		"description": "THE SMALL WEEKENDER BAG IN SIGNATURE ZIG ZAG",
		"color": "009",
		"color_description": "SIGNATURE ZIG ZAG",
		"style": "4IRU0006",
		"size": "U",
		"tray": "2",
		"enabled": "TRUE",
		"soldout": "FALSE"
	},
	{
		"division": "FASHION ACCESSORIES",
		"upc": "716453314198",
		"category": "ROMPER",
		"retail": "150",
		"curr": "USD",
		"description": "JUMP-AROUND JUMPSUIT IN SIGNATURE ZIG ZAG",
		"color": "009",
		"color_description": "SIGNATURE ZIG ZAG",
		"style": "4CMU0003",
		"size": "XS",
		"tray": "2",
		"enabled": "TRUE",
		"soldout": "TRUE"
	},
	{
		"division": "TECH",
		"upc": "716453314174",
		"category": "ROMPER",
		"retail": "150",
		"curr": "USD",
		"description": "JUMP-AROUND JUMPSUIT IN SIGNATURE ZIG ZAG",
		"color": "009",
		"color_description": "SIGNATURE ZIG ZAG",
		"style": "4CMU0003",
		"size": "S",
		"tray": "",
		"enabled": "TRUE",
		"soldout": "FALSE"
	},
	{
		"division": "TECH",
		"upc": "716453314167",
		"category": "ROMPER",
		"retail": "150",
		"curr": "USD",
		"description": "JUMP-AROUND JUMPSUIT IN SIGNATURE ZIG ZAG",
		"color": "009",
		"color_description": "SIGNATURE ZIG ZAG",
		"style": "4CMU0003",
		"size": "M",
		"tray": "",
		"enabled": "TRUE",
		"soldout": "FALSE"
	},
	{
		"division": "home",
		"upc": "716453314150",
		"category": "ROMPER",
		"retail": "150",
		"curr": "USD",
		"description": "JUMP-AROUND JUMPSUIT IN SIGNATURE ZIG ZAG",
		"color": "009",
		"color_description": "SIGNATURE ZIG ZAG",
		"style": "4CMU0003",
		"size": "L",
		"tray": "",
		"enabled": "TRUE",
		"soldout": "FALSE"
	},
	{
		"division": "eyewear",
		"upc": "098689483313",
		"category": "EXTRAS",
		"retail": "35",
		"curr": "USD",
		"description": "EVERYDAY UMBRELLA IN SIGNATURE ZIG ZAG",
		"color": "009",
		"color_description": "SIGNATURE ZIG ZAG",
		"style": "4KRU0008",
		"size": "U",
		"tray": "2",
		"enabled": "TRUE",
		"soldout": "FALSE"
	},
	{
		"division": "eyewear",
		"upc": "098689483627",
		"category": "IPHONE",
		"retail": "25",
		"curr": "USD",
		"description": "IPHONE 5 CASE",
		"color": "009",
		"color_description": "SIGNATURE ZIG ZAG",
		"style": "4LRU0004",
		"size": "U",
		"tray": "2",
		"enabled": "TRUE",
		"soldout": "FALSE"
	},
	{
		"division": "eyewear",
		"upc": "098689483511",
		"category": "IPHONE",
		"retail": "25",
		"curr": "USD",
		"description": "IPHONE 4 CASE",
		"color": "009",
		"color_description": "SIGNATURE ZIG ZAG",
		"style": "4LRU0003",
		"size": "U",
		"tray": "",
		"enabled": "TRUE",
		"soldout": "FALSE"
	},
	{
		"division": "eyewear",
		"upc": "098689486185",
		"category": "EXTRAS",
		"retail": "30",
		"curr": "USD",
		"description": "BIG TIC TAC TOE",
		"color": "125",
		"color_description": "NATURAL",
		"style": "4WRU0004",
		"size": "U",
		"tray": "2",
		"enabled": "TRUE",
		"soldout": "FALSE"
	},
	{
		"division": "HANDBAGS",
		"upc": "098689483870",
		"category": "CORE",
		"retail": "50",
		"curr": "USD",
		"description": "SQUARED SUNNIES",
		"color": "001",
		"color_description": "BLACK",
		"style": "4NRU0002",
		"size": "U",
		"tray": "2",
		"enabled": "TRUE",
		"soldout": "FALSE"
	},
	{
		"division": "APPAREL",
		"upc": "098689483887",
		"category": "CORE",
		"retail": "50",
		"curr": "USD",
		"description": "SQUARED SUNNIES",
		"color": "290",
		"color_description": "TAUPE",
		"style": "4NRU0002",
		"size": "U",
		"tray": "",
		"enabled": "TRUE",
		"soldout": "FALSE"
	},
	{
		"division": "APPAREL",
		"upc": "098689483894",
		"category": "CORE",
		"retail": "50",
		"curr": "USD",
		"description": "SQUARED SUNNIES",
		"color": "687",
		"color_description": "DEEP GREEN",
		"style": "4NRU0002",
		"size": "U",
		"tray": "",
		"enabled": "TRUE",
		"soldout": "FALSE"
	},
	{
		"division": "APPAREL",
		"upc": "098689483900",
		"category": "CORE",
		"retail": "50",
		"curr": "USD",
		"description": "SQUARED SUNNIES",
		"color": "901",
		"color_description": "TORTOISE",
		"style": "4NRU0002",
		"size": "U",
		"tray": "",
		"enabled": "TRUE",
		"soldout": "TRUE"
	},
	{
		"division": "TECH",
		"upc": "716453379036",
		"category": "DRESS",
		"retail": "150",
		"curr": "USD",
		"description": "PLEATED SCOOPBACK DRESS",
		"color": "451",
		"color_description": "CERULEAN",
		"style": "4CMU0174",
		"size": "XS",
		"tray": "3",
		"enabled": "TRUE",
		"soldout": "FALSE"
	},
	{
		"division": "JEWELRY",
		"upc": "716453379012",
		"category": "DRESS",
		"retail": "150",
		"curr": "USD",
		"description": "PLEATED SCOOPBACK DRESS",
		"color": "451",
		"color_description": "CERULEAN",
		"style": "4CMU0174",
		"size": "S",
		"tray": "",
		"enabled": "TRUE",
		"soldout": "FALSE"
	},
	{
		"division": "JEWELRY",
		"upc": "716453379005",
		"category": "DRESS",
		"retail": "150",
		"curr": "USD",
		"description": "PLEATED SCOOPBACK DRESS",
		"color": "451",
		"color_description": "CERULEAN",
		"style": "4CMU0174",
		"size": "M",
		"tray": "",
		"enabled": "TRUE",
		"soldout": "FALSE"
	},
	{
		"division": "SLGS",
		"upc": "716453378992",
		"category": "DRESS",
		"retail": "150",
		"curr": "USD",
		"description": "PLEATED SCOOPBACK DRESS",
		"color": "451",
		"color_description": "CERULEAN",
		"style": "4CMU0174",
		"size": "L",
		"tray": "",
		"enabled": "TRUE",
		"soldout": "FALSE"
	},
	{
		"division": "SLGS",
		"upc": "098689519852",
		"category": "FASHION FABRIC",
		"retail": "110",
		"curr": "USD",
		"description": "COOLER TOTE",
		"color": "088",
		"color_description": "MUSHROOM",
		"style": "4IRU0050",
		"size": "U",
		"tray": "",
		"enabled": "TRUE",
		"soldout": "FALSE"
	},
	{
		"division": "HANDBAGS",
		"upc": "098689519869",
		"category": "FASHION FABRIC",
		"retail": "110",
		"curr": "USD",
		"description": "COOLER TOTE",
		"color": "421",
		"color_description": "CERULEAN",
		"style": "4IRU0050",
		"size": "U",
		"tray": "3",
		"enabled": "TRUE",
		"soldout": "FALSE"
	},
	{
		"division": "APPAREL",
		"upc": "098689519876",
		"category": "FASHION FABRIC",
		"retail": "110",
		"curr": "USD",
		"description": "COOLER TOTE",
		"color": "701",
		"color_description": "YELLOW",
		"style": "4IRU0050",
		"size": "U",
		"tray": "",
		"enabled": "TRUE",
		"soldout": "FALSE"
	},
	{
		"division": "APPAREL",
		"upc": "098689520346",
		"category": "IPHONE",
		"retail": "25",
		"curr": "USD",
		"description": "IPHONE 5 CASE",
		"color": "421",
		"color_description": "CERULEAN OMBRE",
		"style": "4LRU0004",
		"size": "U",
		"tray": "3",
		"enabled": "TRUE",
		"soldout": "FALSE"
	},
	{
		"division": "APPAREL",
		"upc": "098689583709",
		"category": "IPHONE",
		"retail": "25",
		"curr": "USD",
		"description": "IPHONE 4 CASE",
		"color": "421",
		"color_description": "CERULEAN OMBRE",
		"style": "4LRU0003",
		"size": "U",
		"tray": "",
		"enabled": "TRUE",
		"soldout": "FALSE"
	},
	{
		"division": "APPAREL",
		"upc": "098686426191",
		"category": "FASHION",
		"retail": "50",
		"curr": "USD",
		"description": "CORDED KNOT NECKLACE",
		"color": "449",
		"color_description": "DARK BLUE",
		"style": "4VRU0028",
		"size": "U",
		"tray": "3",
		"enabled": "TRUE",
		"soldout": "FALSE"
	},
	{
		"division": "HANDBAGS",
		"upc": "098686426207",
		"category": "FASHION",
		"retail": "50",
		"curr": "USD",
		"description": "CORDED KNOT NECKLACE",
		"color": "672",
		"color_description": "MAGENTA",
		"style": "4VRU0028",
		"size": "U",
		"tray": "",
		"enabled": "TRUE",
		"soldout": "FALSE"
	},
	{
		"division": "FASHION ACCESSORIES",
		"upc": "098689517490",
		"category": "CORE FABRIC",
		"retail": "25",
		"curr": "USD",
		"description": "ZIPPERED POUCH",
		"color": "421",
		"color_description": "CERULEAN",
		"style": "4JRU0087",
		"size": "U",
		"tray": "3",
		"enabled": "TRUE",
		"soldout": "FALSE"
	},
	{
		"division": "HANDBAGS",
		"upc": "098689517506",
		"category": "CORE FABRIC",
		"retail": "25",
		"curr": "USD",
		"description": "ZIPPERED POUCH",
		"color": "672",
		"color_description": "MAGENTA",
		"style": "4JRU0087",
		"size": "U",
		"tray": "",
		"enabled": "TRUE",
		"soldout": "FALSE"
	},
	{
		"division": "apparel",
		"upc": "098689519517",
		"category": "CORE FABRIC",
		"retail": "170",
		"curr": "USD",
		"description": "THE WEEKENDER",
		"color": "421",
		"color_description": "CERULEAN",
		"style": "4IRU0008",
		"size": "U",
		"tray": "3",
		"enabled": "TRUE",
		"soldout": "FALSE"
	},
	{
		"division": "apparel",
		"upc": "716453370293",
		"category": "OUTERWEAR",
		"retail": "140",
		"curr": "USD",
		"description": "DEAN JACKET IN INDIGO FLORAL",
		"color": "404",
		"color_description": "INDIGO FLORAL",
		"style": "4CMU0132",
		"size": "XS",
		"tray": "3",
		"enabled": "TRUE",
		"soldout": "FALSE"
	},
	{
		"division": "apparel",
		"upc": "716453370279",
		"category": "OUTERWEAR",
		"retail": "140",
		"curr": "USD",
		"description": "DEAN JACKET IN INDIGO FLORAL",
		"color": "404",
		"color_description": "INDIGO FLORAL",
		"style": "4CMU0132",
		"size": "S",
		"tray": "",
		"enabled": "TRUE",
		"soldout": "FALSE"
	},
	{
		"division": "apparel",
		"upc": "716453370262",
		"category": "OUTERWEAR",
		"retail": "140",
		"curr": "USD",
		"description": "DEAN JACKET IN INDIGO FLORAL",
		"color": "404",
		"color_description": "INDIGO FLORAL",
		"style": "4CMU0132",
		"size": "M",
		"tray": "",
		"enabled": "TRUE",
		"soldout": "FALSE"
	},
	{
		"division": "SHOES",
		"upc": "716453370255",
		"category": "OUTERWEAR",
		"retail": "140",
		"curr": "USD",
		"description": "DEAN JACKET IN INDIGO FLORAL",
		"color": "404",
		"color_description": "INDIGO FLORAL",
		"style": "4CMU0132",
		"size": "L",
		"tray": "",
		"enabled": "TRUE",
		"soldout": "FALSE"
	},
	{
		"division": "SHOES",
		"upc": "098689516585",
		"category": "FASHION FABRIC",
		"retail": "110",
		"curr": "USD",
		"description": "ORIGAMI TOTE IN INDIGO FLORAL",
		"color": "406",
		"color_description": "INDIGO FLORAL",
		"style": "4IRU0053",
		"size": "U",
		"tray": "3",
		"enabled": "TRUE",
		"soldout": "FALSE"
	},
	{
		"division": "SHOES",
		"upc": "098689517704",
		"category": "HATS",
		"retail": "50",
		"curr": "USD",
		"description": "REVERSIBLE SUNHAT IN BUSY FLORAL",
		"color": "924",
		"color_description": "BUSY FLORAL",
		"style": "4KRU0022",
		"size": "U",
		"tray": "3",
		"enabled": "TRUE",
		"soldout": "FALSE"
	},
	{
		"division": "APPAREL",
		"upc": "716453372068",
		"category": "SKIRT",
		"retail": "95",
		"curr": "USD",
		"description": "GATHER-ROUND MINI SKIRT IN BUSY FLORAL",
		"color": "924",
		"color_description": "BUSY FLORAL",
		"style": "4CMU0143",
		"size": "XS",
		"tray": "3",
		"enabled": "FALSE",
		"soldout": "FALSE"
	},
	{
		"division": "SHOES",
		"upc": "716453368924",
		"category": "WOVEN TOP",
		"retail": "65",
		"curr": "USD",
		"description": "CROP-TIE TOP IN PAINTED CHECK",
		"color": "628",
		"color_description": "PAINTED CHECK",
		"style": "4CMU0124",
		"size": "XS",
		"tray": "3",
		"enabled": "FALSE",
		"soldout": "FALSE"
	},
	{
		"division": "SHOES",
		"upc": "716453368900",
		"category": "WOVEN TOP",
		"retail": "65",
		"curr": "USD",
		"description": "CROP-TIE TOP IN PAINTED CHECK",
		"color": "628",
		"color_description": "PAINTED CHECK",
		"style": "4CMU0124",
		"size": "S",
		"tray": "",
		"enabled": "FALSE",
		"soldout": "FALSE"
	},
	{
		"division": "APPAREL",
		"upc": "716453368894",
		"category": "WOVEN TOP",
		"retail": "65",
		"curr": "USD",
		"description": "CROP-TIE TOP IN PAINTED CHECK",
		"color": "628",
		"color_description": "PAINTED CHECK",
		"style": "4CMU0124",
		"size": "M",
		"tray": "",
		"enabled": "FALSE",
		"soldout": "FALSE"
	},
	{
		"division": "APPAREL",
		"upc": "716453368887",
		"category": "WOVEN TOP",
		"retail": "65",
		"curr": "USD",
		"description": "CROP-TIE TOP IN PAINTED CHECK",
		"color": "628",
		"color_description": "PAINTED CHECK",
		"style": "4CMU0124",
		"size": "L",
		"tray": "",
		"enabled": "FALSE",
		"soldout": "FALSE"
	},
	{
		"division": "APPAREL",
		"upc": "098689521015",
		"category": "CORE",
		"retail": "65",
		"curr": "USD",
		"description": "KATE SPADE SATURDAY SNEAKS BY PF FLYERS",
		"color": "404",
		"color_description": "INDIGO FLORAL",
		"style": "4RRU0006",
		"size": "5",
		"tray": "3",
		"enabled": "TRUE",
		"soldout": "FALSE"
	},
	{
		"division": "APPAREL",
		"upc": "098689521022",
		"category": "CORE",
		"retail": "65",
		"curr": "USD",
		"description": "KATE SPADE SATURDAY SNEAKS BY PF FLYERS",
		"color": "404",
		"color_description": "INDIGO FLORAL",
		"style": "4RRU0006",
		"size": "6",
		"tray": "",
		"enabled": "TRUE",
		"soldout": "FALSE"
	},
	{
		"division": "APPAREL",
		"upc": "098689521039",
		"category": "CORE",
		"retail": "65",
		"curr": "USD",
		"description": "KATE SPADE SATURDAY SNEAKS BY PF FLYERS",
		"color": "404",
		"color_description": "INDIGO FLORAL",
		"style": "4RRU0006",
		"size": "7",
		"tray": "",
		"enabled": "TRUE",
		"soldout": "FALSE"
	},
	{
		"division": "APPAREL",
		"upc": "098689521046",
		"category": "CORE",
		"retail": "65",
		"curr": "USD",
		"description": "KATE SPADE SATURDAY SNEAKS BY PF FLYERS",
		"color": "404",
		"color_description": "INDIGO FLORAL",
		"style": "4RRU0006",
		"size": "8",
		"tray": "",
		"enabled": "TRUE",
		"soldout": "FALSE"
	},
	{
		"division": "APPAREL",
		"upc": "098689521053",
		"category": "CORE",
		"retail": "65",
		"curr": "USD",
		"description": "KATE SPADE SATURDAY SNEAKS BY PF FLYERS",
		"color": "404",
		"color_description": "INDIGO FLORAL",
		"style": "4RRU0006",
		"size": "9",
		"tray": "",
		"enabled": "TRUE",
		"soldout": "FALSE"
	},
	{
		"division": "APPAREL",
		"upc": "098689520995",
		"category": "CORE",
		"retail": "65",
		"curr": "USD",
		"description": "KATE SPADE SATURDAY SNEAKS BY PF FLYERS",
		"color": "404",
		"color_description": "INDIGO FLORAL",
		"style": "4RRU0006",
		"size": "10",
		"tray": "",
		"enabled": "TRUE",
		"soldout": "FALSE"
	},
	{
		"division": "APPAREL",
		"upc": "716453372068",
		"category": "SKIRT",
		"retail": "95",
		"curr": "USD",
		"description": "GATHER-ROUND MINI SKIRT IN BUSY FLORAL",
		"color": "924",
		"color_description": "BUSY FLORAL",
		"style": "4CMU0143",
		"size": "XS",
		"tray": "1,2,3",
		"enabled": "FALSE",
		"soldout": "FALSE"
	},
	{
		"division": "APPAREL",
		"upc": "716453372044",
		"category": "SKIRT",
		"retail": "95",
		"curr": "USD",
		"description": "GATHER-ROUND MINI SKIRT IN BUSY FLORAL",
		"color": "924",
		"color_description": "BUSY FLORAL",
		"style": "4CMU0143",
		"size": "S",
		"tray": "",
		"enabled": "FALSE",
		"soldout": "FALSE"
	},
	{
		"division": "APPAREL",
		"upc": "716453372037",
		"category": "SKIRT",
		"retail": "95",
		"curr": "USD",
		"description": "GATHER-ROUND MINI SKIRT IN BUSY FLORAL",
		"color": "924",
		"color_description": "BUSY FLORAL",
		"style": "4CMU0143",
		"size": "M",
		"tray": "",
		"enabled": "FALSE",
		"soldout": "FALSE"
	},
	{
		"division": "APPAREL",
		"upc": "716453372020",
		"category": "SKIRT",
		"retail": "95",
		"curr": "USD",
		"description": "GATHER-ROUND MINI SKIRT IN BUSY FLORAL",
		"color": "924",
		"color_description": "BUSY FLORAL",
		"style": "4CMU0143",
		"size": "L",
		"tray": "",
		"enabled": "FALSE",
		"soldout": "FALSE"
	}
]